algo_pay/__init__.py
algo_pay/core.py
algo_pay/notifier.py
algo_pay/payroll.py
algo_pay/transactions.py
contracts/__init__.py
contracts/generate_escrow.py
algopay-0.1.7.dist-info/METADATA
algopay-0.1.7.dist-info/WHEEL
algopay-0.1.7.dist-info/licenses/LICENSE
algopay-0.1.7.dist-info/RECORD
