Metadata-Version: 2.4
Name: algopay
Version: 0.1.7
Summary: Open-source Algorand payroll & payments toolkit (multi-department, schedulers, escrow, logging, notifications)
Project-URL: Homepage, https://github.com/KelvinLinBU/Algopay
Project-URL: Source, https://github.com/KelvinLinBU/Algopay
Project-URL: Issues, https://github.com/KelvinLinBU/Algopay/issues
Author: Kelvin Lin
License: MIT
License-File: LICENSE
Keywords: algorand,blockchain,crypto,escrow,payments,payroll
Classifier: Development Status :: 3 - Alpha
Classifier: Intended Audience :: Developers
Classifier: License :: OSI Approved :: MIT License
Classifier: Programming Language :: Python
Classifier: Programming Language :: Python :: 3
Classifier: Programming Language :: Python :: 3 :: Only
Classifier: Programming Language :: Python :: 3.10
Classifier: Programming Language :: Python :: 3.11
Classifier: Programming Language :: Python :: 3.12
Classifier: Topic :: Office/Business :: Financial :: Accounting
Classifier: Topic :: Software Development :: Libraries :: Python Modules
Requires-Python: >=3.10
Requires-Dist: pandas>=1.5.0
Requires-Dist: py-algorand-sdk>=2.4.0
Requires-Dist: pyteal>=0.25.0
Requires-Dist: python-dotenv>=1.0.0
Requires-Dist: schedule>=1.2.0
